<?xml version="1.0" encoding="utf-8"?>
<Deployment xmlns="http://schemas.microsoft.com/windowsphone/2012/deployment" AppPlatformVersion="8.0">
  <DefaultLanguage xmlns="" code="sv" />
  <Languages xmlns="">
    <Language code="sv" />
    <Language code="sv-SE" />
  </Languages>
  <App xmlns="" ProductID="{863bc33d-0a72-4fa5-a463-9f4ba9ea2007}" Title="Styr&amp;Ställ (unofficial)" RuntimeType="Silverlight" Version="1.0.0.0" Genre="apps.normal" Author="Mårten Rånge" Description="Styr&amp;Ställ (unofficial)" Publisher="VRONGE" PublisherID="{853eb1dc-535e-4ed4-a029-7ffd6d150629}">
    <IconPath IsRelative="true" IsResource="false">Assets\ApplicationIcon.png</IconPath>
    <Capabilities>
      <Capability Name="ID_CAP_NETWORKING" />
      <Capability Name="ID_CAP_SENSORS" />
      <Capability Name="ID_CAP_WEBBROWSERCOMPONENT" />
      <Capability Name="ID_CAP_LOCATION" />
      <Capability Name="ID_CAP_MAP" />
    </Capabilities>
    <Tasks>
      <DefaultTask Name="_default" NavigationPage="Pages/StationsPage.xaml" />
    </Tasks>
    <Tokens>
      <PrimaryToken TokenID="SASBikes.WP8Token" TaskName="_default">
        <TemplateFlip>
          <SmallImageURI IsRelative="true" IsResource="false">Assets\Tiles\FlipCycleTileSmall.png</SmallImageURI>
          <Count>0</Count>
          <BackgroundImageURI IsRelative="true" IsResource="false">Assets\Tiles\FlipCycleTileMedium.png</BackgroundImageURI>
          <Title>SASBikes.WP8</Title>
          <BackContent>
          </BackContent>
          <BackBackgroundImageURI>
          </BackBackgroundImageURI>
          <BackTitle>
          </BackTitle>
          <DeviceLockImageURI>
          </DeviceLockImageURI>
          <HasLarge>
          </HasLarge>
        </TemplateFlip>
      </PrimaryToken>
    </Tokens>
    <ScreenResolutions>
      <ScreenResolution Name="ID_RESOLUTION_WVGA" />
      <ScreenResolution Name="ID_RESOLUTION_WXGA" />
      <ScreenResolution Name="ID_RESOLUTION_HD720P" />
    </ScreenResolutions>
  </App>
</Deployment>